mailcore_aiosmtplib/__init__.py
mailcore_aiosmtplib/adapter.py
mailcore_aiosmtplib-0.1.0.dist-info/METADATA
mailcore_aiosmtplib-0.1.0.dist-info/WHEEL
mailcore_aiosmtplib-0.1.0.dist-info/licenses/LICENSE
mailcore_aiosmtplib-0.1.0.dist-info/RECORD
