Metadata-Version: 2.4
Name: mailcore-aiosmtplib
Version: 0.1.0
Summary: aiosmtplib adapter for mailcore
Author-email: "Hans Christian v. Stockhausen" <hc@vst.io>
License: MIT
License-File: LICENSE
Keywords: adapter,aiosmtplib,async,email,mailcore,smtp
Classifier: Development Status :: 3 - Alpha
Classifier: Framework :: AsyncIO
Classifier: Intended Audience :: Developers
Classifier: License :: OSI Approved :: MIT License
Classifier: Programming Language :: Python :: 3
Classifier: Programming Language :: Python :: 3.10
Classifier: Programming Language :: Python :: 3.11
Classifier: Programming Language :: Python :: 3.12
Classifier: Topic :: Communications :: Email
Classifier: Topic :: Software Development :: Libraries :: Python Modules
Requires-Python: >=3.10
Requires-Dist: aiosmtplib>=3.0.0
Requires-Dist: mailcore<1.0.0,>=0.1.0
Provides-Extra: dev
Requires-Dist: detect-secrets; extra == 'dev'
Requires-Dist: httpx>=0.24.0; extra == 'dev'
Requires-Dist: mypy>=1.0.0; extra == 'dev'
Requires-Dist: pre-commit; extra == 'dev'
Requires-Dist: pytest-asyncio>=0.21.0; extra == 'dev'
Requires-Dist: pytest-cov>=4.0.0; extra == 'dev'
Requires-Dist: pytest>=7.0.0; extra == 'dev'
Requires-Dist: ruff>=0.1.0; extra == 'dev'
